EAM/__init__.py
EAM/align_mesh.py
EAM/display.py
EAM/graph.py
EAM/register.py
electroanatomycloud-0.1.0.dist-info/METADATA
electroanatomycloud-0.1.0.dist-info/WHEEL
electroanatomycloud-0.1.0.dist-info/top_level.txt
electroanatomycloud-0.1.0.dist-info/RECORD
