Metadata-Version: 2.4
Name: ElectroAnatomyCloud
Version: 0.1.0
Summary: Tools for processing and visualizing electroanatomic cardiac mesh data
Author-email: Your Name <you@example.com>
Requires-Python: >=3.9
Requires-Dist: numpy
Requires-Dist: SimpleITK
Requires-Dist: scikit-learn
Requires-Dist: scipy
Requires-Dist: trimesh
Requires-Dist: matplotlib
Requires-Dist: plotly
Requires-Dist: scikit-image
